gcloud_oauth_headers/__init__.py
gcloud_oauth_headers/__main__.py
gcloud_oauth_headers/auth.py
gcloud_auth_headers-1.0.1.dist-info/LICENSE
gcloud_auth_headers-1.0.1.dist-info/METADATA
gcloud_auth_headers-1.0.1.dist-info/WHEEL
gcloud_auth_headers-1.0.1.dist-info/entry_points.txt
gcloud_auth_headers-1.0.1.dist-info/top_level.txt
gcloud_auth_headers-1.0.1.dist-info/RECORD
